LICENSE
MANIFEST.in
README.rst
setup.cfg
setup.py
versioneer.py
jupyterhub_terraformspawner.egg-info/PKG-INFO
jupyterhub_terraformspawner.egg-info/SOURCES.txt
jupyterhub_terraformspawner.egg-info/dependency_links.txt
jupyterhub_terraformspawner.egg-info/entry_points.txt
jupyterhub_terraformspawner.egg-info/requires.txt
jupyterhub_terraformspawner.egg-info/top_level.txt
terraformspawner/__init__.py
terraformspawner/__main__.py
terraformspawner/_version.py
terraformspawner/cli.py
terraformspawner/terraformspawner.py
terraformspawner/templates/singleuser.tf